{
  "errorMessage": null,
  "filename": "xdr2.xml",
  "ccdaDocumentType": "CCD",
  "results": {
    "finalGrade": "D",
    "finalNumericalGrade": 68,
    "categoryList": [
      {
        "categoryName": "Miscellaneous",
        "categoryGrade": "A+",
        "categoryNumericalScore": 100,
        "categoryRubrics": [
          {
            "rule": "Generally, the identifiers found within a CDA document should be unique and non-reoccurring within the same document.",
            "numberOfIssues": 0,
            "issuesList": [],
            "exampleTaskForceLinks": [],
            "igReferences": [],
            "description": null
          }
        ],
        "numberOfIssues": 0,
        "certificationFeedback": false,
        "failingConformance": false,
        "nullFlavorNI": false
      },
      {
        "categoryName": "Patient Demographics",
        "categoryGrade": "A+",
        "categoryNumericalScore": 100,
        "categoryRubrics": [
          {
            "rule": "Patient DOB should be valid and properly precisioned",
            "numberOfIssues": 0,
            "issuesList": [],
            "exampleTaskForceLinks": [],
            "igReferences": [],
            "description": null
          },
          {
            "rule": "Patient's Alternative Name Rule",
            "numberOfIssues": 0,
            "issuesList": [],
            "exampleTaskForceLinks": [],
            "igReferences": [],
            "description": null
          }
        ],
        "numberOfIssues": 0,
        "certificationFeedback": false,
        "failingConformance": false,
        "nullFlavorNI": false
      },
      {
        "categoryName": "Allergies",
        "categoryGrade": "D",
        "categoryNumericalScore": 50,
        "categoryRubrics": [
          {
            "rule": "EffectiveDate/Time elements have the right time and timezone offsets",
            "numberOfIssues": 2,
            "issuesList": [
              {
                "lineNumber": "457 - 459",
                "xmlString": "<effectiveTime xmlns:xsi=\"http://www.w3.org/2001/XMLSchema-instance\" xsi:type=\"IVL_TS\">\n                <low nullFlavor=\"NI\"/>\n              </effectiveTime>"
              },
              {
                "lineNumber": "468 - 470",
                "xmlString": "<effectiveTime xmlns:xsi=\"http://www.w3.org/2001/XMLSchema-instance\" xsi:type=\"IVL_TS\">\n                    <low nullFlavor=\"NI\"/>\n                  </effectiveTime>"
              }
            ],
            "exampleTaskForceLinks": [
              "https://github.com/brettmarquard/HL7-C-CDA-Task-Force-Examples/blob/master/No_Known_Allergies_Status_with_Author_Timestamp.xml"
            ],
            "igReferences": [
              "Section 3.5: Allergy Concern Act"
            ],
            "description": "EffectiveTime elements in the section are expected to have timeoffsets along with the date and are typically nonzero timeoffsets. In addition they are expected to have the timezone information for proper interpretation.For e.g if the time is being defaulted to 000000 for hours, minutes and seconds for multiple entries it might be worth checking if the data was entered properly. Also if the time offsets are present without a timezone, the time may be interpreted incorrectly, hence timezones should be specified as part of the time element."
          },
          {
            "rule": "EffectiveDate/Times for all historical activities should be within the lifespan on the patient",
            "numberOfIssues": 0,
            "issuesList": [],
            "exampleTaskForceLinks": [],
            "igReferences": [],
            "description": null
          },
          {
            "rule": "The Display Names used by the structured data should match the Display Name (Preferred Name) within the Terminology",
            "numberOfIssues": 0,
            "issuesList": [],
            "exampleTaskForceLinks": [],
            "igReferences": [],
            "description": null
          },
          {
            "rule": "Allergies Concern observation effective times reflect the appropriate allergy concern status",
            "numberOfIssues": 1,
            "issuesList": [
              {
                "lineNumber": "468 - 470",
                "xmlString": "<effectiveTime xmlns:xsi=\"http://www.w3.org/2001/XMLSchema-instance\" xsi:type=\"IVL_TS\">\n                    <low nullFlavor=\"NI\"/>\n                  </effectiveTime>"
              }
            ],
            "exampleTaskForceLinks": [
              "https://github.com/brettmarquard/HL7-C-CDA-Task-Force-Examples/blob/master/No_Known_Allergies_Status_with_Author_Timestamp.xml"
            ],
            "igReferences": [
              "Section 2.4.1: Allergies and Intolerances Section"
            ],
            "description": "An Allergy Concern of completed or suspended should have an allergy observation effectiveTime/high value present.Similarly an allergy Concern which is Active shall not have an Allergy observation effectiveTime/high value."
          },
          {
            "rule": "Each entry has to be linked to related narrative text",
            "numberOfIssues": 1,
            "issuesList": [
              {
                "lineNumber": "450 - 487",
                "xmlString": "<act xmlns:xsi=\"http://www.w3.org/2001/XMLSchema-instance\" classCode=\"ACT\" moodCode=\"EVN\">\n              <templateId extension=\"2015-08-01\" root=\"2.16.840.1.113883.10.20.22.4.30\"/>\n              <templateId root=\"2.16.840.1.113883.10.20.22.4.30\"/>\n              <id extension=\"14983900007\" root=\"1.3.6.1.4.1.22812.3.2009333.3.4.10\"/>\n              <id extension=\"14983900009\" root=\"1.3.6.1.4.1.22812.3.2009333.3.4.10\"/>\n              <code code=\"CONC\" codeSystem=\"2.16.840.1.113883.5.6\"/>\n              <statusCode code=\"active\"/>\n              <effectiveTime xsi:type=\"IVL_TS\">\n                <low nullFlavor=\"NI\"/>\n              </effectiveTime>\n              <entryRelationship typeCode=\"SUBJ\">\n                <observation classCode=\"OBS\" moodCode=\"EVN\">\n                  <templateId extension=\"2014-06-09\" root=\"2.16.840.1.113883.10.20.22.4.7\"/>\n                  <templateId root=\"2.16.840.1.113883.10.20.22.4.7\"/>\n                  <id extension=\"14983900007\" root=\"1.3.6.1.4.1.22812.3.2009333.3.4.10.2\"/>\n                  <id extension=\"14983900009\" root=\"1.3.6.1.4.1.22812.3.2009333.3.4.10.2\"/>\n                  <code code=\"ASSERTION\" codeSystem=\"2.16.840.1.113883.5.4\"/>\n                  <statusCode code=\"completed\"/>\n                  <effectiveTime xsi:type=\"IVL_TS\">\n                    <low nullFlavor=\"NI\"/>\n                  </effectiveTime>\n                  <value code=\"416098002\" codeSystem=\"2.16.840.1.113883.6.96\" xsi:type=\"CD\">\n                    <originalText>\n                      <reference value=\"#_cccb62d2-58c6-4479-b623-24fa2f6d7116\"/>\n                    </originalText>\n                  </value>\n                  <participant typeCode=\"CSM\">\n                    <participantRole classCode=\"MANU\">\n                      <playingEntity classCode=\"MMAT\">\n                        <code code=\"1191\" codeSystem=\"2.16.840.1.113883.6.88\">\n                          <translation code=\"293586001\" codeSystem=\"2.16.840.1.113883.6.96\"/>\n                        </code>\n                      </playingEntity>\n                    </participantRole>\n                  </participant>\n                </observation>\n              </entryRelationship>\n            </act>"
              }
            ],
            "exampleTaskForceLinks": [
              "https://github.com/brettmarquard/HL7-C-CDA-Task-Force-Examples/blob/master/No_Known_Allergies_Status_with_Author_Timestamp.xml"
            ],
            "igReferences": [
              "Section 2.4.1: Allergies and Intolerances Section"
            ],
            "description": "Each entry has to be linked to related narrative text"
          },
          {
            "rule": "All Template Ids should be Valid with correct extension value",
            "numberOfIssues": 0,
            "issuesList": [],
            "exampleTaskForceLinks": [],
            "igReferences": [],
            "description": null
          }
        ],
        "numberOfIssues": 4,
        "certificationFeedback": false,
        "failingConformance": false,
        "nullFlavorNI": false
      },
      {
        "categoryName": "Encounters",
        "categoryGrade": "D",
        "categoryNumericalScore": 60,
        "categoryRubrics": [
          {
            "rule": "EffectiveDate/Time elements have the right time and timezone offsets",
            "numberOfIssues": 1,
            "issuesList": [
              {
                "lineNumber": "1117 - 1119",
                "xmlString": "<effectiveTime xmlns:xsi=\"http://www.w3.org/2001/XMLSchema-instance\" xsi:type=\"IVL_TS\">\n                <low value=\"20150622130000\"/>\n              </effectiveTime>"
              }
            ],
            "exampleTaskForceLinks": [
              "https://github.com/jddamore/HL7-Task-Force-Examples/blob/master/ENC_Encounter_hospitalization_with_diagnoses.xml"
            ],
            "igReferences": [
              "Section 3.23: Encounter Actvity"
            ],
            "description": "EffectiveTime elements in the section are expected to have timeoffsets along with the date and are typically nonzero timeoffsets. In addition they are expected to have the timezone information for proper interpretation.For e.g if the time is being defaulted to 000000 for hours, minutes and seconds for multiple entries it might be worth checking if the data was entered properly. Also if the time offsets are present without a timezone, the time may be interpreted incorrectly, hence timezones should be specified as part of the time element."
          },
          {
            "rule": "EffectiveDate/Times for all historical activities should be within the lifespan on the patient",
            "numberOfIssues": 1,
            "issuesList": [
              {
                "lineNumber": "1117 - 1119",
                "xmlString": "<effectiveTime xmlns:xsi=\"http://www.w3.org/2001/XMLSchema-instance\" xsi:type=\"IVL_TS\">\n                <low value=\"20150622130000\"/>\n              </effectiveTime>"
              }
            ],
            "exampleTaskForceLinks": [
              "https://github.com/jddamore/HL7-Task-Force-Examples/blob/master/ENC_Encounter_hospitalization_with_diagnoses.xml"
            ],
            "igReferences": [
              "Section 3.23: Encounter Actvity"
            ],
            "description": " EffectiveDate/Times for historical events should be greater than the patient's date of birth and less than the earliest of current time or patient's date of death. "
          },
          {
            "rule": "The Display Names used by the structured data should match the Display Name (Preferred Name) within the Terminology",
            "numberOfIssues": 0,
            "issuesList": [],
            "exampleTaskForceLinks": [],
            "igReferences": [],
            "description": null
          },
          {
            "rule": "Each entry has to be linked to related narrative text",
            "numberOfIssues": 0,
            "issuesList": [],
            "exampleTaskForceLinks": [],
            "igReferences": [],
            "description": null
          },
          {
            "rule": "All Template Ids should be Valid with correct extension value",
            "numberOfIssues": 0,
            "issuesList": [],
            "exampleTaskForceLinks": [],
            "igReferences": [],
            "description": null
          }
        ],
        "numberOfIssues": 2,
        "certificationFeedback": false,
        "failingConformance": false,
        "nullFlavorNI": false
      },
      {
        "categoryName": "Immunizations",
        "categoryGrade": "D",
        "categoryNumericalScore": 67,
        "categoryRubrics": [
          {
            "rule": "EffectiveDate/Time elements have the right time and timezone offsets",
            "numberOfIssues": 1,
            "issuesList": [
              {
                "lineNumber": "681 - 705",
                "xmlString": "<substanceAdministration xmlns:xsi=\"http://www.w3.org/2001/XMLSchema-instance\" classCode=\"SBADM\" moodCode=\"EVN\" negationInd=\"true\">\n              <templateId extension=\"2015-08-01\" root=\"2.16.840.1.113883.10.20.22.4.52\"/>\n              <templateId root=\"2.16.840.1.113883.10.20.22.4.52\"/>\n              <id nullFlavor=\"NI\"/>\n              <text>\n                <reference value=\"#_d46c02d0-8dcb-43b0-bdd1-13617c7e60ae\"/>\n              </text>\n              <statusCode code=\"completed\"/>\n              <effectiveTime nullFlavor=\"NI\"/>\n              <consumable>\n                <manufacturedProduct classCode=\"MANU\">\n                  <templateId extension=\"2014-06-09\" root=\"2.16.840.1.113883.10.20.22.4.54\"/>\n                  <templateId root=\"2.16.840.1.113883.10.20.22.4.54\"/>\n                  <manufacturedMaterial>\n                    <code codeSystem=\"2.16.840.1.113883.12.292\" nullFlavor=\"OTH\">\n                      <originalText>\n                        <reference value=\"#_194a9c17-8479-41c0-9fe0-7b8133253465\"/>\n                      </originalText>\n                      <translation code=\"410942007\" codeSystem=\"2.16.840.1.113883.6.96\"/>\n                    </code>\n                    <lotNumberText nullFlavor=\"NI\"/>\n                  </manufacturedMaterial>\n                </manufacturedProduct>\n              </consumable>\n            </substanceAdministration>"
              }
            ],
            "exampleTaskForceLinks": [
              "https://github.com/brettmarquard/HL7-C-CDA-Task-Force-Examples/blob/master/Unknown_Immunization_Status_R2.xml"
            ],
            "igReferences": [
              "Section 3.41: Immunization Activity"
            ],
            "description": "EffectiveTime elements in the section are expected to have timeoffsets along with the date and are typically nonzero timeoffsets. In addition they are expected to have the timezone information for proper interpretation.For e.g if the time is being defaulted to 000000 for hours, minutes and seconds for multiple entries it might be worth checking if the data was entered properly. Also if the time offsets are present without a timezone, the time may be interpreted incorrectly, hence timezones should be specified as part of the time element."
          },
          {
            "rule": "EffectiveDate/Times for all historical activities should be within the lifespan on the patient",
            "numberOfIssues": 0,
            "issuesList": [],
            "exampleTaskForceLinks": [],
            "igReferences": [],
            "description": null
          },
          {
            "rule": "The Display Names used by the structured data should match the Display Name (Preferred Name) within the Terminology",
            "numberOfIssues": 0,
            "issuesList": [],
            "exampleTaskForceLinks": [],
            "igReferences": [],
            "description": null
          },
          {
            "rule": "Immunizations coded with CVX codes",
            "numberOfIssues": 1,
            "issuesList": [
              {
                "lineNumber": "691 - 703",
                "xmlString": "<manufacturedProduct xmlns:xsi=\"http://www.w3.org/2001/XMLSchema-instance\" classCode=\"MANU\">\n                  <templateId extension=\"2014-06-09\" root=\"2.16.840.1.113883.10.20.22.4.54\"/>\n                  <templateId root=\"2.16.840.1.113883.10.20.22.4.54\"/>\n                  <manufacturedMaterial>\n                    <code codeSystem=\"2.16.840.1.113883.12.292\" nullFlavor=\"OTH\">\n                      <originalText>\n                        <reference value=\"#_194a9c17-8479-41c0-9fe0-7b8133253465\"/>\n                      </originalText>\n                      <translation code=\"410942007\" codeSystem=\"2.16.840.1.113883.6.96\"/>\n                    </code>\n                    <lotNumberText nullFlavor=\"NI\"/>\n                  </manufacturedMaterial>\n                </manufacturedProduct>"
              }
            ],
            "exampleTaskForceLinks": [
              "https://github.com/brettmarquard/HL7-C-CDA-Task-Force-Examples/blob/master/Unknown_Immunization_Status_R2.xml"
            ],
            "igReferences": [
              "Section 3.41: Immunization Activity"
            ],
            "description": "Each Immunization code should be validated aganist CVX Vaccines Administered valueset"
          },
          {
            "rule": "Each entry has to be linked to related narrative text",
            "numberOfIssues": 0,
            "issuesList": [],
            "exampleTaskForceLinks": [],
            "igReferences": [],
            "description": null
          },
          {
            "rule": "All Template Ids should be Valid with correct extension value",
            "numberOfIssues": 0,
            "issuesList": [],
            "exampleTaskForceLinks": [],
            "igReferences": [],
            "description": null
          }
        ],
        "numberOfIssues": 2,
        "certificationFeedback": false,
        "failingConformance": false,
        "nullFlavorNI": false
      },
      {
        "categoryName": "Laboratory Tests and Results",
        "categoryGrade": "D",
        "categoryNumericalScore": 50,
        "categoryRubrics": [
          {
            "rule": "EffectiveDate/Time elements have the right time and timezone offsets",
            "numberOfIssues": 2,
            "issuesList": [
              {
                "lineNumber": "880 - 883",
                "xmlString": "<effectiveTime xmlns:xsi=\"http://www.w3.org/2001/XMLSchema-instance\" xsi:type=\"IVL_TS\">\n                <low nullFlavor=\"NI\"/>\n                <high nullFlavor=\"NI\"/>\n              </effectiveTime>"
              },
              {
                "lineNumber": "885 - 894",
                "xmlString": "<observation xmlns:xsi=\"http://www.w3.org/2001/XMLSchema-instance\" classCode=\"OBS\" moodCode=\"EVN\" negationInd=\"true\">\n                  <templateId extension=\"2015-08-01\" root=\"2.16.840.1.113883.10.20.22.4.2\"/>\n                  <templateId root=\"2.16.840.1.113883.10.20.22.4.2\"/>\n                  <id nullFlavor=\"NI\"/>\n                  <code nullFlavor=\"NI\"/>\n                  <text>Results not documented</text>\n                  <statusCode code=\"completed\"/>\n                  <effectiveTime nullFlavor=\"NI\"/>\n                  <value nullFlavor=\"NI\" xsi:type=\"ST\"/>\n                </observation>"
              }
            ],
            "exampleTaskForceLinks": [
              "https://github.com/jddamore/HL7-Task-Force-Examples/blob/master/RESULT_Value_Less_Than_Physical_Quantity.xml"
            ],
            "igReferences": [
              "Section 3.93: Result Organizer"
            ],
            "description": "EffectiveTime elements in the section are expected to have timeoffsets along with the date and are typically nonzero timeoffsets. In addition they are expected to have the timezone information for proper interpretation.For e.g if the time is being defaulted to 000000 for hours, minutes and seconds for multiple entries it might be worth checking if the data was entered properly. Also if the time offsets are present without a timezone, the time may be interpreted incorrectly, hence timezones should be specified as part of the time element."
          },
          {
            "rule": "EffectiveDate/Times for all historical activities should be within the lifespan on the patient",
            "numberOfIssues": 0,
            "issuesList": [],
            "exampleTaskForceLinks": [],
            "igReferences": [],
            "description": null
          },
          {
            "rule": "The Display Names used by the structured data should match the Display Name (Preferred Name) within the Terminology",
            "numberOfIssues": 0,
            "issuesList": [],
            "exampleTaskForceLinks": [],
            "igReferences": [],
            "description": null
          },
          {
            "rule": "Lab Result values should use preferred UCUM units",
            "numberOfIssues": 1,
            "issuesList": [
              {
                "lineNumber": "885 - 894",
                "xmlString": "<observation xmlns:xsi=\"http://www.w3.org/2001/XMLSchema-instance\" classCode=\"OBS\" moodCode=\"EVN\" negationInd=\"true\">\n                  <templateId extension=\"2015-08-01\" root=\"2.16.840.1.113883.10.20.22.4.2\"/>\n                  <templateId root=\"2.16.840.1.113883.10.20.22.4.2\"/>\n                  <id nullFlavor=\"NI\"/>\n                  <code nullFlavor=\"NI\"/>\n                  <text>Results not documented</text>\n                  <statusCode code=\"completed\"/>\n                  <effectiveTime nullFlavor=\"NI\"/>\n                  <value nullFlavor=\"NI\" xsi:type=\"ST\"/>\n                </observation>"
              }
            ],
            "exampleTaskForceLinks": [
              "https://github.com/jddamore/HL7-Task-Force-Examples/blob/master/RESULT_Value_UCUM_Translation.xml"
            ],
            "igReferences": [
              "Section 3.92: Result Observation"
            ],
            "description": "Lab Results should use the <a href=\"/scorecard/resources/LOINC.csv\">top 2000 LOINC codes and their corresponding units</a> as a best practice."
          },
          {
            "rule": "Lab results should be expressed with LOINC codes",
            "numberOfIssues": 1,
            "issuesList": [
              {
                "lineNumber": "885 - 894",
                "xmlString": "<observation xmlns:xsi=\"http://www.w3.org/2001/XMLSchema-instance\" classCode=\"OBS\" moodCode=\"EVN\" negationInd=\"true\">\n                  <templateId extension=\"2015-08-01\" root=\"2.16.840.1.113883.10.20.22.4.2\"/>\n                  <templateId root=\"2.16.840.1.113883.10.20.22.4.2\"/>\n                  <id nullFlavor=\"NI\"/>\n                  <code nullFlavor=\"NI\"/>\n                  <text>Results not documented</text>\n                  <statusCode code=\"completed\"/>\n                  <effectiveTime nullFlavor=\"NI\"/>\n                  <value nullFlavor=\"NI\" xsi:type=\"ST\"/>\n                </observation>"
              }
            ],
            "exampleTaskForceLinks": [
              "https://github.com/jddamore/HL7-Task-Force-Examples/blob/master/RESULT_Value_UCUM_Translation.xml"
            ],
            "igReferences": [
              "Section 3.92: Result Observation"
            ],
            "description": "Lab results should be expressed with LOINC codes"
          },
          {
            "rule": "The EffectiveDate/Time elements for the Result Organizer must encompass the underlying observations",
            "numberOfIssues": 0,
            "issuesList": [],
            "exampleTaskForceLinks": [],
            "igReferences": [],
            "description": null
          },
          {
            "rule": "Each entry has to be linked to related narrative text",
            "numberOfIssues": 1,
            "issuesList": [
              {
                "lineNumber": "885 - 894",
                "xmlString": "<observation xmlns:xsi=\"http://www.w3.org/2001/XMLSchema-instance\" classCode=\"OBS\" moodCode=\"EVN\" negationInd=\"true\">\n                  <templateId extension=\"2015-08-01\" root=\"2.16.840.1.113883.10.20.22.4.2\"/>\n                  <templateId root=\"2.16.840.1.113883.10.20.22.4.2\"/>\n                  <id nullFlavor=\"NI\"/>\n                  <code nullFlavor=\"NI\"/>\n                  <text>Results not documented</text>\n                  <statusCode code=\"completed\"/>\n                  <effectiveTime nullFlavor=\"NI\"/>\n                  <value nullFlavor=\"NI\" xsi:type=\"ST\"/>\n                </observation>"
              }
            ],
            "exampleTaskForceLinks": [
              "https://github.com/jddamore/HL7-Task-Force-Examples/blob/master/RESULT_Value_Less_Than_Physical_Quantity.xml"
            ],
            "igReferences": [
              "Section 2.64.1: Results Section"
            ],
            "description": "Each entry has to be linked to related narrative text"
          },
          {
            "rule": "All Template Ids should be Valid with correct extension value",
            "numberOfIssues": 0,
            "issuesList": [],
            "exampleTaskForceLinks": [],
            "igReferences": [],
            "description": null
          }
        ],
        "numberOfIssues": 5,
        "certificationFeedback": false,
        "failingConformance": false,
        "nullFlavorNI": false
      },
      {
        "categoryName": "Medications",
        "categoryGrade": "C",
        "categoryNumericalScore": 71,
        "categoryRubrics": [
          {
            "rule": "EffectiveDate/Time elements have the right time and timezone offsets",
            "numberOfIssues": 1,
            "issuesList": [
              {
                "lineNumber": "541 - 544",
                "xmlString": "<effectiveTime xmlns:xsi=\"http://www.w3.org/2001/XMLSchema-instance\" xsi:type=\"IVL_TS\">\n                <low value=\"20160920000000\"/>\n                <high nullFlavor=\"NI\"/>\n              </effectiveTime>"
              }
            ],
            "exampleTaskForceLinks": [
              "https://github.com/jddamore/HL7-Task-Force-Examples/blob/master/MED_Oral_Med_QID_with_PRN.xml"
            ],
            "igReferences": [
              "Section 3.48 Medication Activity"
            ],
            "description": "EffectiveTime elements in the section are expected to have timeoffsets along with the date and are typically nonzero timeoffsets. In addition they are expected to have the timezone information for proper interpretation.For e.g if the time is being defaulted to 000000 for hours, minutes and seconds for multiple entries it might be worth checking if the data was entered properly. Also if the time offsets are present without a timezone, the time may be interpreted incorrectly, hence timezones should be specified as part of the time element."
          },
          {
            "rule": "EffectiveDate/Times for all historical activities should be within the lifespan on the patient",
            "numberOfIssues": 1,
            "issuesList": [
              {
                "lineNumber": "541 - 544",
                "xmlString": "<effectiveTime xmlns:xsi=\"http://www.w3.org/2001/XMLSchema-instance\" xsi:type=\"IVL_TS\">\n                <low value=\"20160920000000\"/>\n                <high nullFlavor=\"NI\"/>\n              </effectiveTime>"
              }
            ],
            "exampleTaskForceLinks": [
              "https://github.com/jddamore/HL7-Task-Force-Examples/blob/master/MED_Oral_Med_QID_with_PRN.xml"
            ],
            "igReferences": [
              "Section 3.48 Medication Activity"
            ],
            "description": " EffectiveDate/Times for historical events should be greater than the patient's date of birth and less than the earliest of current time or patient's date of death. "
          },
          {
            "rule": "The Display Names used by the structured data should match the Display Name (Preferred Name) within the Terminology",
            "numberOfIssues": 0,
            "issuesList": [],
            "exampleTaskForceLinks": [],
            "igReferences": [],
            "description": null
          },
          {
            "rule": "Medications coded with RxNorm SCD, SBD, GPCK, or BPCPK codes",
            "numberOfIssues": 0,
            "issuesList": [],
            "exampleTaskForceLinks": [],
            "igReferences": [],
            "description": null
          },
          {
            "rule": "Each entry has to be linked to related narrative text",
            "numberOfIssues": 0,
            "issuesList": [],
            "exampleTaskForceLinks": [],
            "igReferences": [],
            "description": null
          },
          {
            "rule": "Each medication needs to have its own Medication Signture Text EntryRelationship and the reference should exist in the same section where you found it",
            "numberOfIssues": 0,
            "issuesList": [],
            "exampleTaskForceLinks": [],
            "igReferences": [],
            "description": null
          },
          {
            "rule": "All Template Ids should be Valid with correct extension value",
            "numberOfIssues": 1,
            "issuesList": [
              {
                "lineNumber": "493",
                "xmlString": "<templateId extension=\"2014-06-09\" root=\"2.16.840.1.113883.10.20.22.2.1\"/>"
              }
            ],
            "exampleTaskForceLinks": [
              "https://github.com/brettmarquard/HL7-C-CDA-Task-Force-Examples/blob/master/No_Known_Allergies_Status_with_Author_Timestamp.xml"
            ],
            "igReferences": [
              "Section 2.4.1: Allergies and Intolerances Section"
            ],
            "description": "All Template Ids should be present with valid extension value"
          }
        ],
        "numberOfIssues": 3,
        "certificationFeedback": false,
        "failingConformance": false,
        "nullFlavorNI": false
      },
      {
        "categoryName": "Problems",
        "categoryGrade": "C",
        "categoryNumericalScore": 79,
        "categoryRubrics": [
          {
            "rule": "EffectiveDate/Time elements have the right time and timezone offsets",
            "numberOfIssues": 2,
            "issuesList": [
              {
                "lineNumber": "389 - 391",
                "xmlString": "<effectiveTime xmlns:xsi=\"http://www.w3.org/2001/XMLSchema-instance\" xsi:type=\"IVL_TS\">\n                <low nullFlavor=\"NI\"/>\n              </effectiveTime>"
              },
              {
                "lineNumber": "405 - 407",
                "xmlString": "<effectiveTime xmlns:xsi=\"http://www.w3.org/2001/XMLSchema-instance\" xsi:type=\"IVL_TS\">\n                    <low nullFlavor=\"NI\"/>\n                  </effectiveTime>"
              }
            ],
            "exampleTaskForceLinks": [
              "https://github.com/brettmarquard/HL7-C-CDA-Task-Force-Examples/blob/master/No_Known_Problems_Section_20140226.xml"
            ],
            "igReferences": [
              "Section 3.78: Problem Concern Act"
            ],
            "description": "EffectiveTime elements in the section are expected to have timeoffsets along with the date and are typically nonzero timeoffsets. In addition they are expected to have the timezone information for proper interpretation.For e.g if the time is being defaulted to 000000 for hours, minutes and seconds for multiple entries it might be worth checking if the data was entered properly. Also if the time offsets are present without a timezone, the time may be interpreted incorrectly, hence timezones should be specified as part of the time element."
          },
          {
            "rule": "EffectiveDate/Times for all historical activities should be within the lifespan on the patient",
            "numberOfIssues": 0,
            "issuesList": [],
            "exampleTaskForceLinks": [],
            "igReferences": [],
            "description": null
          },
          {
            "rule": "The Display Names used by the structured data should match the Display Name (Preferred Name) within the Terminology",
            "numberOfIssues": 0,
            "issuesList": [],
            "exampleTaskForceLinks": [],
            "igReferences": [],
            "description": null
          },
          {
            "rule": "All problem codes are should express with core subset of SNOMED codes",
            "numberOfIssues": 0,
            "issuesList": [],
            "exampleTaskForceLinks": [],
            "igReferences": [],
            "description": null
          },
          {
            "rule": "Problem Concern effective times reflect the appropriate problem concern status",
            "numberOfIssues": 1,
            "issuesList": [
              {
                "lineNumber": "405 - 407",
                "xmlString": "<effectiveTime xmlns:xsi=\"http://www.w3.org/2001/XMLSchema-instance\" xsi:type=\"IVL_TS\">\n                    <low nullFlavor=\"NI\"/>\n                  </effectiveTime>"
              }
            ],
            "exampleTaskForceLinks": [
              "https://github.com/brettmarquard/HL7-C-CDA-Task-Force-Examples/blob/master/No_Known_Problems_Section_20140226.xml"
            ],
            "igReferences": [
              "Section 3.78: Problem Concern Act"
            ],
            "description": "A Problem Concern of completed or suspended should have a Problem Concern effectiveTime/high value present.Similarly a Problem Concern which is Active shall not have a Problem Concern effectiveTime/high value."
          },
          {
            "rule": "Each entry has to be linked to related narrative text",
            "numberOfIssues": 2,
            "issuesList": [
              {
                "lineNumber": "345 - 379",
                "xmlString": "<act xmlns:xsi=\"http://www.w3.org/2001/XMLSchema-instance\" classCode=\"ACT\" moodCode=\"EVN\">\n              <templateId extension=\"2015-08-01\" root=\"2.16.840.1.113883.10.20.22.4.3\"/>\n              <templateId root=\"2.16.840.1.113883.10.20.22.4.3\"/>\n              <id extension=\"14952300007\" root=\"1.3.6.1.4.1.22812.3.2009333.3.4.1\"/>\n              <id extension=\"14980100001\" root=\"1.3.6.1.4.1.22812.3.2009333.3.4.1\"/>\n              <code code=\"CONC\" codeSystem=\"2.16.840.1.113883.5.6\"/>\n              <statusCode code=\"active\"/>\n              <effectiveTime xsi:type=\"IVL_TS\">\n                <low value=\"20160919\"/>\n              </effectiveTime>\n              <entryRelationship typeCode=\"SUBJ\">\n                <observation classCode=\"OBS\" moodCode=\"EVN\">\n                  <templateId extension=\"2015-08-01\" root=\"2.16.840.1.113883.10.20.22.4.4\"/>\n                  <templateId root=\"2.16.840.1.113883.10.20.22.4.4\"/>\n                  <id extension=\"14952300007\" root=\"1.3.6.1.4.1.22812.3.2009333.3.4.1.2.1\"/>\n                  <id extension=\"14980100001\" root=\"1.3.6.1.4.1.22812.3.2009333.3.4.1.2.1\"/>\n                  <code code=\"55607006\" codeSystem=\"2.16.840.1.113883.6.96\">\n                    <translation nullFlavor=\"NI\"/>\n                  </code>\n                  <text>\n                    <reference value=\"#_2c3d8fd9-3e7f-4c50-a7c0-85164887d7f3\"/>\n                  </text>\n                  <statusCode code=\"completed\"/>\n                  <effectiveTime xsi:type=\"IVL_TS\">\n                    <low value=\"20160919\"/>\n                  </effectiveTime>\n                  <value code=\"55607006\" codeSystem=\"2.16.840.1.113883.6.96\" xsi:type=\"CD\">\n                    <originalText>\n                      <reference value=\"#_2c3d8fd9-3e7f-4c50-a7c0-85164887d7f3\"/>\n                    </originalText>\n                    <translation code=\"5725005\" codeSystem=\"2.16.840.1.113883.3.247.1.1\"/>\n                  </value>\n                </observation>\n              </entryRelationship>\n            </act>"
              },
              {
                "lineNumber": "382 - 418",
                "xmlString": "<act xmlns:xsi=\"http://www.w3.org/2001/XMLSchema-instance\" classCode=\"ACT\" moodCode=\"EVN\">\n              <templateId extension=\"2015-08-01\" root=\"2.16.840.1.113883.10.20.22.4.3\"/>\n              <templateId root=\"2.16.840.1.113883.10.20.22.4.3\"/>\n              <id extension=\"14952300013\" root=\"1.3.6.1.4.1.22812.3.2009333.3.4.1\"/>\n              <id extension=\"14980200005\" root=\"1.3.6.1.4.1.22812.3.2009333.3.4.1\"/>\n              <code code=\"CONC\" codeSystem=\"2.16.840.1.113883.5.6\"/>\n              <statusCode code=\"active\"/>\n              <effectiveTime xsi:type=\"IVL_TS\">\n                <low nullFlavor=\"NI\"/>\n              </effectiveTime>\n              <entryRelationship typeCode=\"SUBJ\">\n                <observation classCode=\"OBS\" moodCode=\"EVN\">\n                  <templateId extension=\"2015-08-01\" root=\"2.16.840.1.113883.10.20.22.4.4\"/>\n                  <templateId root=\"2.16.840.1.113883.10.20.22.4.4\"/>\n                  <id extension=\"14952300013\" root=\"1.3.6.1.4.1.22812.3.2009333.3.4.1.2.1\"/>\n                  <id extension=\"14980200005\" root=\"1.3.6.1.4.1.22812.3.2009333.3.4.1.2.1\"/>\n                  <code code=\"55607006\" codeSystem=\"2.16.840.1.113883.6.96\">\n                    <translation nullFlavor=\"NI\"/>\n                  </code>\n                  <text>\n                    <reference value=\"#_caf03f5b-803a-4586-93aa-9c483cd9b5af\"/>\n                  </text>\n                  <statusCode code=\"completed\"/>\n                  <effectiveTime xsi:type=\"IVL_TS\">\n                    <low nullFlavor=\"NI\"/>\n                  </effectiveTime>\n                  <value code=\"310366008\" codeSystem=\"2.16.840.1.113883.6.96\" xsi:type=\"CD\">\n                    <originalText>\n                      <reference value=\"#_caf03f5b-803a-4586-93aa-9c483cd9b5af\"/>\n                    </originalText>\n                    <translation code=\"V70.0\" codeSystem=\"2.16.840.1.113883.6.103\"/>\n                    <translation code=\"Z00.00\" codeSystem=\"2.16.840.1.113883.6.90\"/>\n                    <translation code=\"1518611\" codeSystem=\"2.16.840.1.113883.3.247.1.1\"/>\n                  </value>\n                </observation>\n              </entryRelationship>\n            </act>"
              }
            ],
            "exampleTaskForceLinks": [
              "https://github.com/brettmarquard/HL7-C-CDA-Task-Force-Examples/blob/master/No_Known_Problems_Section_20140226.xml"
            ],
            "igReferences": [
              "Section 2.53.1: Problem Section"
            ],
            "description": "Each entry has to be linked to related narrative text"
          },
          {
            "rule": "All Template Ids should be Valid with correct extension value",
            "numberOfIssues": 0,
            "issuesList": [],
            "exampleTaskForceLinks": [],
            "igReferences": [],
            "description": null
          }
        ],
        "numberOfIssues": 5,
        "certificationFeedback": false,
        "failingConformance": false,
        "nullFlavorNI": false
      },
      {
        "categoryName": "Procedures",
        "categoryGrade": "A+",
        "categoryNumericalScore": 100,
        "categoryRubrics": [
          {
            "rule": "The Display Names used by the structured data should match the Display Name (Preferred Name) within the Terminology",
            "numberOfIssues": 0,
            "issuesList": [],
            "exampleTaskForceLinks": [],
            "igReferences": [],
            "description": null
          },
          {
            "rule": "Each entry has to be linked to related narrative text",
            "numberOfIssues": 0,
            "issuesList": [],
            "exampleTaskForceLinks": [],
            "igReferences": [],
            "description": null
          },
          {
            "rule": "All Template Ids should be Valid with correct extension value",
            "numberOfIssues": 0,
            "issuesList": [],
            "exampleTaskForceLinks": [],
            "igReferences": [],
            "description": null
          }
        ],
        "numberOfIssues": 0,
        "certificationFeedback": false,
        "failingConformance": false,
        "nullFlavorNI": false
      },
      {
        "categoryName": "Social History",
        "categoryGrade": "C",
        "categoryNumericalScore": 75,
        "categoryRubrics": [
          {
            "rule": "EffectiveDate/Time elements have the right time and timezone offsets",
            "numberOfIssues": 1,
            "issuesList": [
              {
                "lineNumber": "789 - 797",
                "xmlString": "<observation xmlns:xsi=\"http://www.w3.org/2001/XMLSchema-instance\" classCode=\"OBS\" moodCode=\"EVN\">\n              <templateId extension=\"2014-06-09\" root=\"2.16.840.1.113883.10.20.22.4.78\"/>\n              <templateId root=\"2.16.840.1.113883.10.20.22.4.78\"/>\n              <id nullFlavor=\"NI\"/>\n              <code code=\"72166-2\" codeSystem=\"2.16.840.1.113883.6.1\"/>\n              <statusCode code=\"completed\"/>\n              <effectiveTime nullFlavor=\"NI\"/>\n              <value code=\"449868002\" codeSystem=\"2.16.840.1.113883.6.96\" xsi:type=\"CD\"/>\n            </observation>"
              }
            ],
            "exampleTaskForceLinks": [
              "https://github.com/jddamore/HL7-Task-Force-Examples/blob/master/SMOKING_Former_Smoker.xml"
            ],
            "igReferences": [
              "Section 2.66: Social History Section"
            ],
            "description": "EffectiveTime elements in the section are expected to have timeoffsets along with the date and are typically nonzero timeoffsets. In addition they are expected to have the timezone information for proper interpretation.For e.g if the time is being defaulted to 000000 for hours, minutes and seconds for multiple entries it might be worth checking if the data was entered properly. Also if the time offsets are present without a timezone, the time may be interpreted incorrectly, hence timezones should be specified as part of the time element."
          },
          {
            "rule": "EffectiveDate/Times for all historical activities should be within the lifespan on the patient",
            "numberOfIssues": 0,
            "issuesList": [],
            "exampleTaskForceLinks": [],
            "igReferences": [],
            "description": null
          },
          {
            "rule": "The Display Names used by the structured data should match the Display Name (Preferred Name) within the Terminology",
            "numberOfIssues": 0,
            "issuesList": [],
            "exampleTaskForceLinks": [],
            "igReferences": [],
            "description": null
          },
          {
            "rule": "Smoking status code value should be valid",
            "numberOfIssues": 0,
            "issuesList": [],
            "exampleTaskForceLinks": [],
            "igReferences": [],
            "description": null
          },
          {
            "rule": "Smoking status observation Template Id should be valid",
            "numberOfIssues": 0,
            "issuesList": [],
            "exampleTaskForceLinks": [],
            "igReferences": [],
            "description": null
          },
          {
            "rule": "Systems should capture birth sex independent of the Administrative Gender and encode them as an observation in the Social History Section",
            "numberOfIssues": 0,
            "issuesList": [],
            "exampleTaskForceLinks": [],
            "igReferences": [],
            "description": null
          },
          {
            "rule": "Each entry has to be linked to related narrative text",
            "numberOfIssues": 2,
            "issuesList": [
              {
                "lineNumber": "789 - 797",
                "xmlString": "<observation xmlns:xsi=\"http://www.w3.org/2001/XMLSchema-instance\" classCode=\"OBS\" moodCode=\"EVN\">\n              <templateId extension=\"2014-06-09\" root=\"2.16.840.1.113883.10.20.22.4.78\"/>\n              <templateId root=\"2.16.840.1.113883.10.20.22.4.78\"/>\n              <id nullFlavor=\"NI\"/>\n              <code code=\"72166-2\" codeSystem=\"2.16.840.1.113883.6.1\"/>\n              <statusCode code=\"completed\"/>\n              <effectiveTime nullFlavor=\"NI\"/>\n              <value code=\"449868002\" codeSystem=\"2.16.840.1.113883.6.96\" xsi:type=\"CD\"/>\n            </observation>"
              },
              {
                "lineNumber": "781 - 786",
                "xmlString": "<observation xmlns:xsi=\"http://www.w3.org/2001/XMLSchema-instance\" classCode=\"OBS\" moodCode=\"EVN\">\n              <templateId extension=\"2016-06-01\" root=\"2.16.840.1.113883.10.20.22.4.200\"/>\n              <code code=\"76689-9\" codeSystem=\"2.16.840.1.113883.6.1\"/>\n              <statusCode code=\"completed\"/>\n              <value code=\"M\" codeSystem=\"2.16.840.1.113883.5.1\" xsi:type=\"CD\"/>\n            </observation>"
              }
            ],
            "exampleTaskForceLinks": [
              "https://github.com/jddamore/HL7-Task-Force-Examples/blob/master/SMOKING_Former_Smoker.xml"
            ],
            "igReferences": [
              "Section 2.66: Social History Section"
            ],
            "description": "Each entry has to be linked to related narrative text"
          },
          {
            "rule": "All Template Ids should be Valid with correct extension value",
            "numberOfIssues": 0,
            "issuesList": [],
            "exampleTaskForceLinks": [],
            "igReferences": [],
            "description": null
          }
        ],
        "numberOfIssues": 3,
        "certificationFeedback": false,
        "failingConformance": false,
        "nullFlavorNI": false
      },
      {
        "categoryName": "Vital Signs",
        "categoryGrade": "D",
        "categoryNumericalScore": 60,
        "categoryRubrics": [
          {
            "rule": "EffectiveDate/Time elements have the right time and timezone offsets",
            "numberOfIssues": 7,
            "issuesList": [
              {
                "lineNumber": "983 - 983",
                "xmlString": "<effectiveTime xmlns:xsi=\"http://www.w3.org/2001/XMLSchema-instance\" value=\"20160826164600\"/>"
              },
              {
                "lineNumber": "992 - 992",
                "xmlString": "<effectiveTime xmlns:xsi=\"http://www.w3.org/2001/XMLSchema-instance\" value=\"20160826164600\"/>"
              },
              {
                "lineNumber": "1013 - 1013",
                "xmlString": "<effectiveTime xmlns:xsi=\"http://www.w3.org/2001/XMLSchema-instance\" value=\"20160826164600\"/>"
              },
              {
                "lineNumber": "1034 - 1034",
                "xmlString": "<effectiveTime xmlns:xsi=\"http://www.w3.org/2001/XMLSchema-instance\" value=\"20160826164600\"/>"
              },
              {
                "lineNumber": "1046 - 1046",
                "xmlString": "<effectiveTime xmlns:xsi=\"http://www.w3.org/2001/XMLSchema-instance\" value=\"20160826164600\"/>"
              },
              {
                "lineNumber": "1058 - 1058",
                "xmlString": "<effectiveTime xmlns:xsi=\"http://www.w3.org/2001/XMLSchema-instance\" value=\"20160826164600\"/>"
              },
              {
                "lineNumber": "1070 - 1070",
                "xmlString": "<effectiveTime xmlns:xsi=\"http://www.w3.org/2001/XMLSchema-instance\" value=\"20160826164600\"/>"
              }
            ],
            "exampleTaskForceLinks": [
              "https://github.com/jddamore/HL7-Task-Force-Examples/blob/master/VITALS_Complete_Panel_Metric.xml"
            ],
            "igReferences": [
              "Section 3.109: Vital Signs Organizer"
            ],
            "description": "EffectiveTime elements in the section are expected to have timeoffsets along with the date and are typically nonzero timeoffsets. In addition they are expected to have the timezone information for proper interpretation.For e.g if the time is being defaulted to 000000 for hours, minutes and seconds for multiple entries it might be worth checking if the data was entered properly. Also if the time offsets are present without a timezone, the time may be interpreted incorrectly, hence timezones should be specified as part of the time element."
          },
          {
            "rule": "EffectiveDate/Times for all historical activities should be within the lifespan on the patient",
            "numberOfIssues": 7,
            "issuesList": [
              {
                "lineNumber": "983 - 983",
                "xmlString": "<effectiveTime xmlns:xsi=\"http://www.w3.org/2001/XMLSchema-instance\" value=\"20160826164600\"/>"
              },
              {
                "lineNumber": "992 - 992",
                "xmlString": "<effectiveTime xmlns:xsi=\"http://www.w3.org/2001/XMLSchema-instance\" value=\"20160826164600\"/>"
              },
              {
                "lineNumber": "1013 - 1013",
                "xmlString": "<effectiveTime xmlns:xsi=\"http://www.w3.org/2001/XMLSchema-instance\" value=\"20160826164600\"/>"
              },
              {
                "lineNumber": "1034 - 1034",
                "xmlString": "<effectiveTime xmlns:xsi=\"http://www.w3.org/2001/XMLSchema-instance\" value=\"20160826164600\"/>"
              },
              {
                "lineNumber": "1046 - 1046",
                "xmlString": "<effectiveTime xmlns:xsi=\"http://www.w3.org/2001/XMLSchema-instance\" value=\"20160826164600\"/>"
              },
              {
                "lineNumber": "1058 - 1058",
                "xmlString": "<effectiveTime xmlns:xsi=\"http://www.w3.org/2001/XMLSchema-instance\" value=\"20160826164600\"/>"
              },
              {
                "lineNumber": "1070 - 1070",
                "xmlString": "<effectiveTime xmlns:xsi=\"http://www.w3.org/2001/XMLSchema-instance\" value=\"20160826164600\"/>"
              }
            ],
            "exampleTaskForceLinks": [
              "https://github.com/jddamore/HL7-Task-Force-Examples/blob/master/VITALS_Complete_Panel_Metric.xml"
            ],
            "igReferences": [
              "Section 3.109: Vital Signs Organizer"
            ],
            "description": " EffectiveDate/Times for historical events should be greater than the patient's date of birth and less than the earliest of current time or patient's date of death. "
          },
          {
            "rule": "The Display Names used by the structured data should match the Display Name (Preferred Name) within the Terminology",
            "numberOfIssues": 0,
            "issuesList": [],
            "exampleTaskForceLinks": [],
            "igReferences": [],
            "description": null
          },
          {
            "rule": "The Vital Sign Observation entries should use LOINC codes to represent the type of vital sign being captured",
            "numberOfIssues": 1,
            "issuesList": [
              {
                "lineNumber": "1044",
                "xmlString": "<code xmlns:xsi=\"http://www.w3.org/2001/XMLSchema-instance\" code=\"3141-9\" codeSystem=\"2.16.840.1.113883.6.1\"/>"
              }
            ],
            "exampleTaskForceLinks": [
              "https://github.com/jddamore/HL7-Task-Force-Examples/blob/master/VITALS_Complete_Panel_Metric.xml"
            ],
            "igReferences": [
              "Section 3.108: Vital Sign Observation"
            ],
            "description": "Each of the vital sign observation present in the document should use the recommended LOINC codes to represent the vital sign."
          },
          {
            "rule": "Each of the Vital Sign Observations should use the recommended UCUM units to represent the vital sign measurement result",
            "numberOfIssues": 0,
            "issuesList": [],
            "exampleTaskForceLinks": [],
            "igReferences": [],
            "description": null
          },
          {
            "rule": "The EffectiveDate/Time elements for the Vital Sign Organizer must encompass the underlying observations",
            "numberOfIssues": 0,
            "issuesList": [],
            "exampleTaskForceLinks": [],
            "igReferences": [],
            "description": null
          },
          {
            "rule": "Each entry has to be linked to related narrative text",
            "numberOfIssues": 6,
            "issuesList": [
              {
                "lineNumber": "985 - 1003",
                "xmlString": "<observation xmlns:xsi=\"http://www.w3.org/2001/XMLSchema-instance\" classCode=\"OBS\" moodCode=\"EVN\">\n                  <templateId extension=\"2014-06-09\" root=\"2.16.840.1.113883.10.20.22.4.27\"/>\n                  <templateId root=\"2.16.840.1.113883.10.20.22.4.27\"/>\n                  <id extension=\"14952300035\" root=\"1.3.6.1.4.1.22812.3.2009333.3.4.6\"/>\n                  <id extension=\"14952300053\" root=\"1.3.6.1.4.1.22812.3.2009333.3.4.6\"/>\n                  <code code=\"8480-6\" codeSystem=\"2.16.840.1.113883.6.1\"/>\n                  <statusCode code=\"completed\"/>\n                  <effectiveTime value=\"20160826164600\"/>\n                  <value unit=\"mm[Hg]\" value=\"145\" xsi:type=\"PQ\"/>\n                  <entryRelationship inversionInd=\"true\" typeCode=\"SUBJ\">\n                    <act classCode=\"ACT\" moodCode=\"EVN\">\n                      <templateId root=\"2.16.840.1.113883.10.20.22.4.64\"/>\n                      <code code=\"48767-8\" codeSystem=\"2.16.840.1.113883.6.1\"/>\n                      <text>\n                        <reference value=\"#_2f3e67c5-ee29-466e-9207-19b4ce2b2843\"/>\n                      </text>\n                    </act>\n                  </entryRelationship>\n                </observation>"
              },
              {
                "lineNumber": "1006 - 1024",
                "xmlString": "<observation xmlns:xsi=\"http://www.w3.org/2001/XMLSchema-instance\" classCode=\"OBS\" moodCode=\"EVN\">\n                  <templateId extension=\"2014-06-09\" root=\"2.16.840.1.113883.10.20.22.4.27\"/>\n                  <templateId root=\"2.16.840.1.113883.10.20.22.4.27\"/>\n                  <id extension=\"14952300037\" root=\"1.3.6.1.4.1.22812.3.2009333.3.4.6\"/>\n                  <id extension=\"14952300055\" root=\"1.3.6.1.4.1.22812.3.2009333.3.4.6\"/>\n                  <code code=\"8462-4\" codeSystem=\"2.16.840.1.113883.6.1\"/>\n                  <statusCode code=\"completed\"/>\n                  <effectiveTime value=\"20160826164600\"/>\n                  <value unit=\"mm[Hg]\" value=\"88\" xsi:type=\"PQ\"/>\n                  <entryRelationship inversionInd=\"true\" typeCode=\"SUBJ\">\n                    <act classCode=\"ACT\" moodCode=\"EVN\">\n                      <templateId root=\"2.16.840.1.113883.10.20.22.4.64\"/>\n                      <code code=\"48767-8\" codeSystem=\"2.16.840.1.113883.6.1\"/>\n                      <text>\n                        <reference value=\"#_4379e180-b4c5-4fea-b30d-96f2f2351008\"/>\n                      </text>\n                    </act>\n                  </entryRelationship>\n                </observation>"
              },
              {
                "lineNumber": "1027 - 1036",
                "xmlString": "<observation xmlns:xsi=\"http://www.w3.org/2001/XMLSchema-instance\" classCode=\"OBS\" moodCode=\"EVN\">\n                  <templateId extension=\"2014-06-09\" root=\"2.16.840.1.113883.10.20.22.4.27\"/>\n                  <templateId root=\"2.16.840.1.113883.10.20.22.4.27\"/>\n                  <id extension=\"14952300029\" root=\"1.3.6.1.4.1.22812.3.2009333.3.4.6\"/>\n                  <id extension=\"14952300049\" root=\"1.3.6.1.4.1.22812.3.2009333.3.4.6\"/>\n                  <code code=\"8302-2\" codeSystem=\"2.16.840.1.113883.6.1\"/>\n                  <statusCode code=\"completed\"/>\n                  <effectiveTime value=\"20160826164600\"/>\n                  <value unit=\"cm\" value=\"177\" xsi:type=\"PQ\"/>\n                </observation>"
              },
              {
                "lineNumber": "1039 - 1048",
                "xmlString": "<observation xmlns:xsi=\"http://www.w3.org/2001/XMLSchema-instance\" classCode=\"OBS\" moodCode=\"EVN\">\n                  <templateId extension=\"2014-06-09\" root=\"2.16.840.1.113883.10.20.22.4.27\"/>\n                  <templateId root=\"2.16.840.1.113883.10.20.22.4.27\"/>\n                  <id extension=\"14952300027\" root=\"1.3.6.1.4.1.22812.3.2009333.3.4.6\"/>\n                  <id extension=\"14952300047\" root=\"1.3.6.1.4.1.22812.3.2009333.3.4.6\"/>\n                  <code code=\"3141-9\" codeSystem=\"2.16.840.1.113883.6.1\"/>\n                  <statusCode code=\"completed\"/>\n                  <effectiveTime value=\"20160826164600\"/>\n                  <value unit=\"kg\" value=\"88\" xsi:type=\"PQ\"/>\n                </observation>"
              },
              {
                "lineNumber": "1051 - 1060",
                "xmlString": "<observation xmlns:xsi=\"http://www.w3.org/2001/XMLSchema-instance\" classCode=\"OBS\" moodCode=\"EVN\">\n                  <templateId extension=\"2014-06-09\" root=\"2.16.840.1.113883.10.20.22.4.27\"/>\n                  <templateId root=\"2.16.840.1.113883.10.20.22.4.27\"/>\n                  <id extension=\"14952300025\" root=\"1.3.6.1.4.1.22812.3.2009333.3.4.6\"/>\n                  <id extension=\"14952300045\" root=\"1.3.6.1.4.1.22812.3.2009333.3.4.6\"/>\n                  <code code=\"39156-5\" codeSystem=\"2.16.840.1.113883.6.1\"/>\n                  <statusCode code=\"completed\"/>\n                  <effectiveTime value=\"20160826164600\"/>\n                  <value unit=\"kg/m2\" value=\"28.09\" xsi:type=\"PQ\"/>\n                </observation>"
              },
              {
                "lineNumber": "1063 - 1072",
                "xmlString": "<observation xmlns:xsi=\"http://www.w3.org/2001/XMLSchema-instance\" classCode=\"OBS\" moodCode=\"EVN\">\n                  <templateId extension=\"2014-06-09\" root=\"2.16.840.1.113883.10.20.22.4.27\"/>\n                  <templateId root=\"2.16.840.1.113883.10.20.22.4.27\"/>\n                  <id extension=\"14952300023\" root=\"1.3.6.1.4.1.22812.3.2009333.3.4.6\"/>\n                  <id extension=\"14952300043\" root=\"1.3.6.1.4.1.22812.3.2009333.3.4.6\"/>\n                  <code code=\"3140-1\" codeSystem=\"2.16.840.1.113883.6.1\"/>\n                  <statusCode code=\"completed\"/>\n                  <effectiveTime value=\"20160826164600\"/>\n                  <value unit=\"m2\" value=\"2.05\" xsi:type=\"PQ\"/>\n                </observation>"
              }
            ],
            "exampleTaskForceLinks": [
              "https://github.com/jddamore/HL7-Task-Force-Examples/blob/master/VITALS_Complete_Panel_Metric.xml"
            ],
            "igReferences": [
              "Section 2.70.1: Vital Signs Section"
            ],
            "description": "Each entry has to be linked to related narrative text"
          },
          {
            "rule": "All Template Ids should be Valid with correct extension value",
            "numberOfIssues": 0,
            "issuesList": [],
            "exampleTaskForceLinks": [],
            "igReferences": [],
            "description": null
          }
        ],
        "numberOfIssues": 21,
        "certificationFeedback": false,
        "failingConformance": false,
        "nullFlavorNI": false
      }
    ],
    "numberOfIssues": 45,
    "igReferenceUrl": "http://www.hl7.org/implement/standards/product_brief.cfm?product_id=379",
    "industryAverageScore": 79,
    "industryAverageGrade": "C",
    "numberOfDocumentsScored": 33991,
    "ccdaVersion": "R2.1",
    "passedCertification": null,
    "numberOfDocsScoredPerCcdaDocumentType": 19897,
    "industryAverageScoreForCcdaDocumentType": 77,
    "industryAverageGradeForCcdaDocumentType": "C"
  },
  "referenceResults": [
    {
      "type": "C-CDA IG Conformance Errors",
      "totalErrorCount": 0,
      "referenceErrors": []
    },
    {
      "type": "2015 Edition Certification Feedback",
      "totalErrorCount": 1,
      "referenceErrors": [
        {
          "description": "Code C42998 does not exist in the value set(s) 2.16.840.1.113762.1.4.1021.30",
          "type": "ONC 2015 S&CC Vocabulary Validation Conformance Error",
          "xPath": "/ClinicalDocument[1]/component[1]/structuredBody[1]/component[4]/section[1]/entry[1]/substanceAdministration[1]/administrationUnitCode[1]",
          "validatorConfiguredXpath": "//v3:substanceAdministration/v3:templateId[@root='2.16.840.1.113883.10.20.22.4.16' and @extension='2014-06-09']/ancestor::v3:substanceAdministration[1]/v3:administrationUnitCode[not(@nullFlavor) and ancestor::v3:section[not(@nullFlavor)]]",
          "documentLineNumber": "550",
          "actualCode": "C42998",
          "actualCodeSystem": "2.16.840.1.113883.3.26.1.1",
          "actualCodeSystemName": "",
          "actualDisplayName": "",
          "schemaError": false,
          "dataTypeSchemaError": false,
          "sectionName": null
        }
      ]
    }
  ],
  "schemaErrorList": null,
  "schemaErrors": false,
  "success": true
}